voicelint/__init__.py
voicelint/utility.py
voicelint/version.py
voicelint/checkers/__init__.py
voicelint/checkers/conditional_import_checker.py
voicelint/checkers/dyn_checker.py
voicelint/checkers/mimic_checker.py
voicelint/checkers/pause_checker.py
voicelint/checkers/rule_details_checker.py
voicelint-0.1.0.dist-info/LICENSE
voicelint-0.1.0.dist-info/METADATA
voicelint-0.1.0.dist-info/WHEEL
voicelint-0.1.0.dist-info/top_level.txt
voicelint-0.1.0.dist-info/RECORD
