Metadata-Version: 2.1
Name: voicelint
Version: 0.1.0
Summary: pylint plug-in for users of the programing by voice toolkit Caster
Home-page: https://github.com/mpourmpoulis/voicelint
Author: mpourmpoulis
License: UNKNOWN
Platform: UNKNOWN
Classifier: Development Status :: 3 - Alpha
Classifier: Programming Language :: Python :: 3
Classifier: License :: OSI Approved :: BSD License
Classifier: Operating System :: OS Independent
Requires-Python: >=3.0
